sales_prediction_moduls/__init__.py
sales_prediction_moduls/data_preparation.py
sales_prediction_moduls/explainability_layer.py
sales_prediction_moduls/feature_extraction.py
sales_prediction_moduls/hyperopt_tuner.py
sales_prediction_moduls/model_validator.py
ds_sale_prediction_package-0.1.8.dist-info/LICENSE.txt
ds_sale_prediction_package-0.1.8.dist-info/METADATA
ds_sale_prediction_package-0.1.8.dist-info/WHEEL
ds_sale_prediction_package-0.1.8.dist-info/top_level.txt
ds_sale_prediction_package-0.1.8.dist-info/RECORD
